README.md
setup.py
MasalaPipe/LGBM_otm.py
MasalaPipe/__init__.py
MasalaPipe/masala_pipe.py
MasalaPipe/rank_count.py
MasalaPipe.egg-info/PKG-INFO
MasalaPipe.egg-info/SOURCES.txt
MasalaPipe.egg-info/dependency_links.txt
MasalaPipe.egg-info/top_level.txt