Metadata-Version: 2.1
Name: MasalaPipe
Version: 0.0.1
Summary: Python module to classification model using LGBM
Home-page: https://github.com/giovane-sylvestrin/MasalaPipe/tree/main
Author: Giovane Sylvestrin
Author-email: giovane.sylvestrin@gmail.com
Classifier: Programming Language :: Python :: 3
Classifier: License :: OSI Approved :: MIT License
Classifier: Operating System :: OS Independent
Requires-Python: >=3.8
